avionmqtt/Http.py
avionmqtt/Mesh.py
avionmqtt/Mqtt.py
avionmqtt/__init__.py
avionmqtt/__main__.py
avionmqtt/cli.py
avionmqtt/config.py
avionmqtt/csrmeshcrypto.py
avionmqtt/mesh_handler.py
avionmqtt/mqtt_handler.py
avionmqtt/service.py
avionmqtt-2.0.2.dist-info/licenses/LICENSE
avionmqtt-2.0.2.dist-info/METADATA
avionmqtt-2.0.2.dist-info/WHEEL
avionmqtt-2.0.2.dist-info/entry_points.txt
avionmqtt-2.0.2.dist-info/top_level.txt
avionmqtt-2.0.2.dist-info/RECORD
