Metadata-Version: 2.4
Name: avionmqtt
Version: 2.0.2
Summary: Bridge Avion Bluetooth mesh lights to MQTT/Home Assistant
Author-email: Sean Kinsey <oyvind@kinsey.no>
Maintainer-email: Sean Kinsey <oyvind@kinsey.no>
License: LGPL-3.0-or-later
Project-URL: Homepage, https://github.com/oyvindkinsey/avionmqtt
Project-URL: Repository, https://github.com/oyvindkinsey/avionmqtt
Project-URL: Issues, https://github.com/oyvindkinsey/avionmqtt/issues
Project-URL: Documentation, https://github.com/oyvindkinsey/avionmqtt/blob/main/README.md
Keywords: avion,bluetooth,mesh,mqtt,home-assistant,smart-home,iot
Classifier: Development Status :: 4 - Beta
Classifier: Intended Audience :: Developers
Classifier: License :: OSI Approved :: GNU Lesser General Public License v3 (LGPLv3)
Classifier: Programming Language :: Python :: 3
Classifier: Programming Language :: Python :: 3.11
Classifier: Programming Language :: Python :: 3.12
Classifier: Topic :: Home Automation
Classifier: Topic :: System :: Hardware
Requires-Python: >=3.11
License-File: LICENSE
Requires-Dist: aiohttp>=3.7
Requires-Dist: aiomqtt>=2.0.0
Requires-Dist: aiorun>=2022.11.1
Requires-Dist: bleak>=0.21.0
Requires-Dist: pycryptodomex>=3.23.0
Requires-Dist: pyyaml>=6.0
Provides-Extra: dev
Requires-Dist: pytest>=7.4.0; extra == "dev"
Requires-Dist: pytest-asyncio>=0.21.0; extra == "dev"
Requires-Dist: pytest-cov>=4.1.0; extra == "dev"
Requires-Dist: pytest-mock>=3.11.0; extra == "dev"
Requires-Dist: black>=23.7.0; extra == "dev"
Requires-Dist: isort>=5.12.0; extra == "dev"
Requires-Dist: flake8>=6.1.0; extra == "dev"
Requires-Dist: mypy>=1.5.0; extra == "dev"
Requires-Dist: pre-commit>=3.3.0; extra == "dev"
Provides-Extra: test
Requires-Dist: pytest>=7.4.0; extra == "test"
Requires-Dist: pytest-asyncio>=0.21.0; extra == "test"
Requires-Dist: pytest-cov>=4.1.0; extra == "test"
Requires-Dist: pytest-mock>=3.11.0; extra == "test"
Dynamic: license-file
